{
  "slug": "word-search",
  "title": "Word Search",
  "difficulty": "medium",
  "tags": [
    "backtracking",
    "matrix",
    "depth-first-search"
  ],
  "languages": [
    "python"
  ],
  "limits": {
    "timeLimitMs": 10000,
    "memoryLimitMb": 512
  },
  "function": {
    "name": "exist",
    "params": [
      {
        "name": "board",
        "type": "string[][]"
      },
      {
        "name": "word",
        "type": "string"
      }
    ],
    "returns": {
      "type": "bool"
    }
  },
  "scoring": {
    "type": "weighted",
    "points": 100
  },
  "compare": "exact"
}
