{
  "slug": "largest-values-from-labels",
  "title": "Largest Values From Labels",
  "difficulty": "medium",
  "tags": [
    "array",
    "hash-table",
    "greedy",
    "sorting"
  ],
  "hints": [
    "Focus on the items with the highest values first, since you want to maximize the total sum.",
    "Sort the items by value in descending order and iterate through them to make greedy choices.",
    "Track how many items of each label you have already selected; skip an item if its label count reaches the limit."
  ],
  "languages": [
    "python"
  ],
  "limits": {
    "timeLimitMs": 10000,
    "memoryLimitMb": 512
  },
  "function": {
    "name": "largestValsFromLabels",
    "params": [
      {
        "name": "values",
        "type": "int[]"
      },
      {
        "name": "labels",
        "type": "int[]"
      },
      {
        "name": "numWanted",
        "type": "int"
      },
      {
        "name": "useLimit",
        "type": "int"
      }
    ],
    "returns": {
      "type": "int"
    }
  },
  "scoring": {
    "type": "weighted",
    "points": 100
  },
  "compare": "exact"
}
