{
  "slug": "count-range-sum",
  "title": "Range Sum Count",
  "difficulty": "hard",
  "tags": [
    "array",
    "prefix-sum",
    "sorting"
  ],
  "hints": [
    "Consider prefix sums to transform subarray sums into differences between two prefix sums.",
    "Use a merge sort based approach to count valid pairs while merging sorted halves.",
    "During the merge step, use two pointers to efficiently count valid prefix sum differences for each element in the left half."
  ],
  "languages": [
    "python"
  ],
  "limits": {
    "timeLimitMs": 10000,
    "memoryLimitMb": 512
  },
  "function": {
    "name": "countRangeSum",
    "params": [
      {
        "name": "nums",
        "type": "int[]"
      },
      {
        "name": "lower",
        "type": "int"
      },
      {
        "name": "upper",
        "type": "int"
      }
    ],
    "returns": {
      "type": "int"
    }
  },
  "scoring": {
    "type": "weighted",
    "points": 100
  },
  "compare": "exact"
}
