{
  "slug": "course-schedule-ordering",
  "title": "Course Schedule Ordering",
  "difficulty": "medium",
  "tags": [
    "graph"
  ],
  "hints": [
    "This is a topological sort problem. Check for cycles first; if none exist, an ordering is possible.",
    "Use Kahn's algorithm with a min-heap instead of a queue to ensure lexicographically smallest output.",
    "Initialize the heap with all courses having zero in-degree. Repeatedly extract the minimum, add it to the result, and decrease neighbors' in-degrees."
  ],
  "languages": [
    "python"
  ],
  "limits": {
    "timeLimitMs": 10000,
    "memoryLimitMb": 512
  },
  "function": {
    "name": "findOrder",
    "params": [
      {
        "name": "numCourses",
        "type": "int"
      },
      {
        "name": "prerequisites",
        "type": "int[][]"
      }
    ],
    "returns": {
      "type": "int[]"
    }
  },
  "scoring": {
    "type": "weighted",
    "points": 100
  },
  "compare": "exact"
}
