{
  "slug": "bulls-and-cows",
  "title": "Bulls and Cows",
  "difficulty": "medium",
  "tags": [
    "string",
    "hash-table",
    "counting"
  ],
  "hints": [
    "First, count bulls by comparing characters at identical indices in both strings.",
    "Next, count the frequency of each digit in both strings, ignoring positions already matched as bulls.",
    "Cows equal the sum of minimum frequencies of each digit across both strings, minus the bull count."
  ],
  "languages": [
    "python"
  ],
  "limits": {
    "timeLimitMs": 10000,
    "memoryLimitMb": 512
  },
  "function": {
    "name": "getHint",
    "params": [
      {
        "name": "secret",
        "type": "string"
      },
      {
        "name": "guess",
        "type": "string"
      }
    ],
    "returns": {
      "type": "string"
    }
  },
  "scoring": {
    "type": "weighted",
    "points": 100
  },
  "compare": "exact"
}
