{
  "slug": "continuous-subarray-sum",
  "title": "Continuous Subarray Sum",
  "difficulty": "medium",
  "tags": [
    "array",
    "hash-table",
    "prefix-sum"
  ],
  "hints": [
    "Consider prefix sums and how the difference between two prefix sums relates to subarray sums.",
    "Use the property that if two prefix sums have the same remainder when divided by k, their difference is a multiple of k.",
    "Store the first occurrence of each remainder in a hash map, ensuring the subarray length is at least 2 by checking indices."
  ],
  "languages": [
    "python"
  ],
  "limits": {
    "timeLimitMs": 10000,
    "memoryLimitMb": 512
  },
  "function": {
    "name": "checkSubarraySum",
    "params": [
      {
        "name": "nums",
        "type": "int[]"
      },
      {
        "name": "k",
        "type": "int"
      }
    ],
    "returns": {
      "type": "bool"
    }
  },
  "scoring": {
    "type": "weighted",
    "points": 100
  },
  "compare": "exact"
}
