{
  "slug": "path-sum-exists",
  "title": "Path Sum Exists",
  "difficulty": "easy",
  "tags": [
    "tree",
    "binary-tree",
    "depth-first-search"
  ],
  "hints": [
    "Consider how to traverse the tree while keeping track of the current path sum from the root.",
    "Use Depth First Search to visit nodes, subtracting the current node's value from the remaining target sum at each step.",
    "A leaf node is a valid endpoint only if both its left and right children are None and the remaining sum is zero."
  ],
  "languages": [
    "python"
  ],
  "limits": {
    "timeLimitMs": 10000,
    "memoryLimitMb": 512
  },
  "function": {
    "name": "hasPathSum",
    "params": [
      {
        "name": "root",
        "type": "TreeNode"
      },
      {
        "name": "targetSum",
        "type": "int"
      }
    ],
    "returns": {
      "type": "bool"
    }
  },
  "scoring": {
    "type": "weighted",
    "points": 100
  },
  "compare": "exact"
}
